{
  "id": 24,
  "title": "エンジンコンプレッサ",
  "category": "管工事機械・工具",
  "types": [
    "スクリュー式（ロータリー式",
    "レシプロ式（往復動式",
    "北越工業（AIRMAN） PDSシリーズ",
    "デンヨー（Denyo） DISシリーズ",
    "アトラスコプコ（Atlas Copco）"
  ],
  "purchaseProductTitle": "の買取実績",
  "cameraImagesGallery": [
    {
      "title": "☆北越 AIRMAN エアーマン★エンジンコンプレッサー★PDS70S★235h☆ ",
      "imageSrc": "https://mac-hadis.s3.ap-northeast-1.amazonaws.com/products/%E7%AE%A1%E5%B7%A5%E4%BA%8B%E6%A9%9F%E6%A2%B0%E3%83%BB%E5%B7%A5%E5%85%B7/%E3%82%A8%E3%83%B3%E3%82%B8%E3%83%B3%E3%82%B3%E3%83%B3%E3%83%97%E3%83%AC%E3%83%83%E3%82%B5/cameraImagesGallery/%E2%98%86%E5%8C%97%E8%B6%8A%20AIRMAN%20%E3%82%A8%E3%82%A2%E3%83%BC%E3%83%9E%E3%83%B3%E2%98%85%E3%82%A8%E3%83%B3%E3%82%B8%E3%83%B3%E3%82%B3%E3%83%B3%E3%83%97%E3%83%AC%E3%83%83%E3%82%B5%E3%83%BC%E2%98%85PDS70S%E2%98%85235h%E2%98%86%20.JPG"
    },
    {
      "title": "AIRMAN エアーマン 北越工業★エンジンコンプレッサー★PDR-70S★",
      "imageSrc": "https://mac-hadis.s3.ap-northeast-1.amazonaws.com/products/%E7%AE%A1%E5%B7%A5%E4%BA%8B%E6%A9%9F%E6%A2%B0%E3%83%BB%E5%B7%A5%E5%85%B7/%E3%82%A8%E3%83%B3%E3%82%B8%E3%83%B3%E3%82%B3%E3%83%B3%E3%83%97%E3%83%AC%E3%83%83%E3%82%B5/cameraImagesGallery/AIRMAN%20%E3%82%A8%E3%82%A2%E3%83%BC%E3%83%9E%E3%83%B3%20%E5%8C%97%E8%B6%8A%E5%B7%A5%E6%A5%AD%E2%98%85%E3%82%A8%E3%83%B3%E3%82%B7%E3%82%99%E3%83%B3%E3%82%B3%E3%83%B3%E3%83%95%E3%82%9A%E3%83%AC%E3%83%83%E3%82%B5%E3%83%BC%E2%98%85PDR-70S%E2%98%85.jpeg"
    },
    {
      "title": "北越工業 AIRMAN★防音型 エンジンコンプレッサ ディーゼル★PDR50S",
      "imageSrc": "https://mac-hadis.s3.ap-northeast-1.amazonaws.com/products/%E7%AE%A1%E5%B7%A5%E4%BA%8B%E6%A9%9F%E6%A2%B0%E3%83%BB%E5%B7%A5%E5%85%B7/%E3%82%A8%E3%83%B3%E3%82%B8%E3%83%B3%E3%82%B3%E3%83%B3%E3%83%97%E3%83%AC%E3%83%83%E3%82%B5/cameraImagesGallery/%E5%8C%97%E8%B6%8A%E5%B7%A5%E6%A5%AD%20AIRMAN%E2%98%85%E9%98%B2%E9%9F%B3%E5%9E%8B%20%E3%82%A8%E3%83%B3%E3%82%B8%E3%83%B3%E3%82%B3%E3%83%B3%E3%83%97%E3%83%AC%E3%83%83%E3%82%B5%20%E3%83%87%E3%82%A3%E3%83%BC%E3%82%BC%E3%83%AB%E2%98%85PDR50S.jpg"
    },
    {
      "title": "AIRMAN★スクリューコンプレッサ★PDS100SC AC",
      "imageSrc": "https://mac-hadis.s3.ap-northeast-1.amazonaws.com/products/%E7%AE%A1%E5%B7%A5%E4%BA%8B%E6%A9%9F%E6%A2%B0%E3%83%BB%E5%B7%A5%E5%85%B7/%E3%82%A8%E3%83%B3%E3%82%B8%E3%83%B3%E3%82%B3%E3%83%B3%E3%83%97%E3%83%AC%E3%83%83%E3%82%B5/cameraImagesGallery/AIRMAN%E2%98%85%E3%82%B9%E3%82%AF%E3%83%AA%E3%83%A5%E3%83%BC%E3%82%B3%E3%83%B3%E3%83%97%E3%83%AC%E3%83%83%E3%82%B5%E2%98%85PDS100SC%20AC.jpg"
    },
    {
      "title": "AIRMAN★スクリューコンプレッサ★PDS130S AC",
      "imageSrc": "https://mac-hadis.s3.ap-northeast-1.amazonaws.com/products/%E7%AE%A1%E5%B7%A5%E4%BA%8B%E6%A9%9F%E6%A2%B0%E3%83%BB%E5%B7%A5%E5%85%B7/%E3%82%A8%E3%83%B3%E3%82%B8%E3%83%B3%E3%82%B3%E3%83%B3%E3%83%97%E3%83%AC%E3%83%83%E3%82%B5/cameraImagesGallery/AIRMAN%E2%98%85%E3%82%B9%E3%82%AF%E3%83%AA%E3%83%A5%E3%83%BC%E3%82%B3%E3%83%B3%E3%83%97%E3%83%AC%E3%83%83%E3%82%B5%E2%98%85PDS130S%20AC.jpg"
    },
    {
      "title": "AIRMAN 北越工業★エンジンコンプレッサ★ ★PDS130SC-5C3",
      "imageSrc": "https://mac-hadis.s3.ap-northeast-1.amazonaws.com/products/%E7%AE%A1%E5%B7%A5%E4%BA%8B%E6%A9%9F%E6%A2%B0%E3%83%BB%E5%B7%A5%E5%85%B7/%E3%82%A8%E3%83%B3%E3%82%B8%E3%83%B3%E3%82%B3%E3%83%B3%E3%83%97%E3%83%AC%E3%83%83%E3%82%B5/cameraImagesGallery/AIRMAN%20%E5%8C%97%E8%B6%8A%E5%B7%A5%E6%A5%AD%E2%98%85%E3%82%A8%E3%83%B3%E3%82%B8%E3%83%B3%E3%82%B3%E3%83%B3%E3%83%97%E3%83%AC%E3%83%83%E3%82%B5%E2%98%85%20%E2%98%85PDS130SC-5C3.jpg"
    },
    {
      "title": "北越工業 AIRMAN★エンジンコンプレッサ★  ★PDS175SC-5C3★アフタークーラー★50馬力",
      "imageSrc": "https://mac-hadis.s3.ap-northeast-1.amazonaws.com/products/%E7%AE%A1%E5%B7%A5%E4%BA%8B%E6%A9%9F%E6%A2%B0%E3%83%BB%E5%B7%A5%E5%85%B7/%E3%82%A8%E3%83%B3%E3%82%B8%E3%83%B3%E3%82%B3%E3%83%B3%E3%83%97%E3%83%AC%E3%83%83%E3%82%B5/cameraImagesGallery/%E5%8C%97%E8%B6%8A%E5%B7%A5%E6%A5%AD%20AIRMAN%E2%98%85%E3%82%A8%E3%83%B3%E3%82%B8%E3%83%B3%E3%82%B3%E3%83%B3%E3%83%97%E3%83%AC%E3%83%83%E3%82%B5%E2%98%85%20%20%E2%98%85PDS175SC-5C3%E2%98%85%E3%82%A2%E3%83%95%E3%82%BF%E3%83%BC%E3%82%AF%E3%83%BC%E3%83%A9%E3%83%BC%E2%98%8550%E9%A6%AC%E5%8A%9B.jpg"
    },
    {
      "title": "AIRMAN★エンジンコンプレッサー★  ★PDS185SC-7C5",
      "imageSrc": "https://mac-hadis.s3.ap-northeast-1.amazonaws.com/products/%E7%AE%A1%E5%B7%A5%E4%BA%8B%E6%A9%9F%E6%A2%B0%E3%83%BB%E5%B7%A5%E5%85%B7/%E3%82%A8%E3%83%B3%E3%82%B8%E3%83%B3%E3%82%B3%E3%83%B3%E3%83%97%E3%83%AC%E3%83%83%E3%82%B5/cameraImagesGallery/AIRMAN%E2%98%85%E3%82%A8%E3%83%B3%E3%82%B8%E3%83%B3%E3%82%B3%E3%83%B3%E3%83%97%E3%83%AC%E3%83%83%E3%82%B5%E3%83%BC%E2%98%85%20%20%E2%98%85PDS185SC-7C5.jpg"
    }
  ],
  "webImagesGallery": [
    {
      "title": "エンジンコンプレッサ",
      "imageSrc": "https://mac-hadis.s3.ap-northeast-1.amazonaws.com/products/%E7%AE%A1%E5%B7%A5%E4%BA%8B%E6%A9%9F%E6%A2%B0%E3%83%BB%E5%B7%A5%E5%85%B7/%E3%82%A8%E3%83%B3%E3%82%B8%E3%83%B3%E3%82%B3%E3%83%B3%E3%83%97%E3%83%AC%E3%83%83%E3%82%B5/webImagesGallery/%E3%82%A8%E3%83%B3%E3%82%B8%E3%83%B3%E3%82%B3%E3%83%B3%E3%83%97%E3%83%AC%E3%83%83%E3%82%B5.png"
    },
    {
      "title": "エンジンコンプレッサ",
      "imageSrc": "https://mac-hadis.s3.ap-northeast-1.amazonaws.com/products/%E7%AE%A1%E5%B7%A5%E4%BA%8B%E6%A9%9F%E6%A2%B0%E3%83%BB%E5%B7%A5%E5%85%B7/%E3%82%A8%E3%83%B3%E3%82%B8%E3%83%B3%E3%82%B3%E3%83%B3%E3%83%97%E3%83%AC%E3%83%83%E3%82%B5/webImagesGallery/%E3%82%A8%E3%83%B3%E3%82%B8%E3%83%B3%E3%82%B3%E3%83%B3%E3%83%97%E3%83%AC%E3%83%83%E3%82%B5.png"
    },
    {
      "title": "エンジンコンプレッサ",
      "imageSrc": "https://mac-hadis.s3.ap-northeast-1.amazonaws.com/products/%E7%AE%A1%E5%B7%A5%E4%BA%8B%E6%A9%9F%E6%A2%B0%E3%83%BB%E5%B7%A5%E5%85%B7/%E3%82%A8%E3%83%B3%E3%82%B8%E3%83%B3%E3%82%B3%E3%83%B3%E3%83%97%E3%83%AC%E3%83%83%E3%82%B5/webImagesGallery/%E3%82%A8%E3%83%B3%E3%82%B8%E3%83%B3%E3%82%B3%E3%83%B3%E3%83%97%E3%83%AC%E3%83%83%E3%82%B5.png"
    },
    {
      "title": "エンジンコンプレッサ",
      "imageSrc": "https://mac-hadis.s3.ap-northeast-1.amazonaws.com/products/%E7%AE%A1%E5%B7%A5%E4%BA%8B%E6%A9%9F%E6%A2%B0%E3%83%BB%E5%B7%A5%E5%85%B7/%E3%82%A8%E3%83%B3%E3%82%B8%E3%83%B3%E3%82%B3%E3%83%B3%E3%83%97%E3%83%AC%E3%83%83%E3%82%B5/webImagesGallery/%E3%82%A8%E3%83%B3%E3%82%B8%E3%83%B3%E3%82%B3%E3%83%B3%E3%83%97%E3%83%AC%E3%83%83%E3%82%B5.png"
    },
    {
      "title": "エンジンコンプレッサ",
      "imageSrc": "https://mac-hadis.s3.ap-northeast-1.amazonaws.com/products/%E7%AE%A1%E5%B7%A5%E4%BA%8B%E6%A9%9F%E6%A2%B0%E3%83%BB%E5%B7%A5%E5%85%B7/%E3%82%A8%E3%83%B3%E3%82%B8%E3%83%B3%E3%82%B3%E3%83%B3%E3%83%97%E3%83%AC%E3%83%83%E3%82%B5/webImagesGallery/%E3%82%A8%E3%83%B3%E3%82%B8%E3%83%B3%E3%82%B3%E3%83%B3%E3%83%97%E3%83%AC%E3%83%83%E3%82%B5.png"
    },
    {
      "title": "エンジンコンプレッサ",
      "imageSrc": "https://mac-hadis.s3.ap-northeast-1.amazonaws.com/products/%E7%AE%A1%E5%B7%A5%E4%BA%8B%E6%A9%9F%E6%A2%B0%E3%83%BB%E5%B7%A5%E5%85%B7/%E3%82%A8%E3%83%B3%E3%82%B8%E3%83%B3%E3%82%B3%E3%83%B3%E3%83%97%E3%83%AC%E3%83%83%E3%82%B5/webImagesGallery/%E3%82%A8%E3%83%B3%E3%82%B8%E3%83%B3%E3%82%B3%E3%83%B3%E3%83%97%E3%83%AC%E3%83%83%E3%82%B5.png"
    }
  ],
  "makers": [
    {
      "jp": "",
      "en": "meijiair",
      "link": "https://www.meijiair.co.jp/",
      "imageSrc": "https://mac-hadis.s3.ap-northeast-1.amazonaws.com/products/%E7%AE%A1%E5%B7%A5%E4%BA%8B%E6%A9%9F%E6%A2%B0%E3%83%BB%E5%B7%A5%E5%85%B7/%E3%82%A8%E3%83%B3%E3%82%B8%E3%83%B3%E3%82%B3%E3%83%B3%E3%83%97%E3%83%AC%E3%83%83%E3%82%B5/makers/meijiair.png"
    },
    {
      "jp": "",
      "en": "denyo",
      "link": "https://www.denyo.co.jp/",
      "imageSrc": "https://mac-hadis.s3.ap-northeast-1.amazonaws.com/products/%E7%AE%A1%E5%B7%A5%E4%BA%8B%E6%A9%9F%E6%A2%B0%E3%83%BB%E5%B7%A5%E5%85%B7/%E3%82%A8%E3%83%B3%E3%82%B8%E3%83%B3%E3%82%B3%E3%83%B3%E3%83%97%E3%83%AC%E3%83%83%E3%82%B5/makers/denyo.png"
    },
    {
      "jp": "",
      "en": "airman",
      "link": "https://www.airman.co.jp/",
      "imageSrc": "https://mac-hadis.s3.ap-northeast-1.amazonaws.com/products/%E7%AE%A1%E5%B7%A5%E4%BA%8B%E6%A9%9F%E6%A2%B0%E3%83%BB%E5%B7%A5%E5%85%B7/%E3%82%A8%E3%83%B3%E3%82%B8%E3%83%B3%E3%82%B3%E3%83%B3%E3%83%97%E3%83%AC%E3%83%83%E3%82%B5/makers/airman.png"
    }
  ],
  "information": [
    "サビや汚れ、傷みが少なく綺麗なもの（ただし、再塗装されているものは値打ちが下がる場合があります。）",
    "取扱説明書や付属品が揃っている",
    "製造メーカー、製造年などの情報を把握していること",
    "買取時に動作確認が可能であること"
  ],
  "questions": [
    {
      "id": 1,
      "question": "配線はそのままでも大丈夫ですか？",
      "answer": "はい、当社の技術スタッフが安全に取り外し作業を行います。"
    },
    {
      "id": 2,
      "question": "解体もしてくれますか？",
      "answer": "はい、当社のスタッフが解体作業を行います。"
    },
    {
      "id": 3,
      "question": "現地にフォークリフトやクレーンがないのですが、買取可能ですか？",
      "answer": "はい、必要に応じてリフトや専用の機材・道具を持参し、パワーゲート付きトラックまたはユニック車でお伺いいたします。"
    },
    {
      "id": 4,
      "question": "積み込みの手伝いが必要ですか？",
      "answer": "いいえ、お客様のお手伝いは不要です。搬出から積み込みまで当社のスタッフが対応します。"
    },
    {
      "id": 5,
      "question": "遠方でも買取に来てくれますか？",
      "answer": "はい、日本各地でエンジンコンプレッサの買取実績があります。"
    },
    {
      "id": 6,
      "question": "不要になった金属材料がありますが、処分してくれますか？",
      "answer": "はい、買取の際に引き取り可能です。手数料はかかりません。"
    }
  ],
  "servicesDescription": "ご使用されなくなったエンジンコンプレッサはございませんか？\\n ハディズでは、あらゆるメーカー・型式の中古エンジンコンプレッサの買取を行っております。大型で重量のある機械の搬出・運搬も、専門知識を持つスタッフが安全かつ丁寧に対応いたします。機械の状態を適正に評価し、公正な価格での買取と迅速なお支払いをお約束いたします。"
}